wagtaildependencies/__init__.py
wagtaildependencies/wagtail_hooks.py
wagtaildependencies-0.0.0.dist-info/DESCRIPTION.rst
wagtaildependencies-0.0.0.dist-info/metadata.json
wagtaildependencies-0.0.0.dist-info/WHEEL
wagtaildependencies-0.0.0.dist-info/METADATA
wagtaildependencies-0.0.0.dist-info/RECORD
wagtaildependencies-0.0.0.dist-info/top_level.txt
