Metadata-Version: 2.0
Name: wagtaildependencies
Version: 0.0.0
Summary: Makes it easy to manage front-end dependencies for Wagtail admin plugins
Home-page: https://github.com/alexgleason/wagtaildependencies
Author: Alex Gleason
Author-email: alex@alexgleason.me
License: MIT
Keywords: d,e,v,e,l,o,p,m,e,n,t
Platform: UNKNOWN
Classifier: Environment :: Web Environment
Classifier: Framework :: Django
Classifier: Intended Audience :: Developers
Classifier: Operating System :: OS Independent
Classifier: Programming Language :: Python
Classifier: Topic :: Internet :: WWW/HTTP
Classifier: Topic :: Internet :: WWW/HTTP :: Dynamic Content
Requires-Dist: wagtail (>=1.4.0)
Requires-Dist: Django (>=1.7.1)
